{
  "classTimes": [
    {
      "fullQualifiedName": "com.google.gson.functional.DefaultTypeAdaptersTest",
      "timeInMs": 17877
    },
    {
      "fullQualifiedName": "com.google.gson.functional.MapTest",
      "timeInMs": 79385
    },
    {
      "fullQualifiedName": "com.google.gson.internal.bind.RecursiveTypesResolveTest",
      "timeInMs": 3866
    },
    {
      "fullQualifiedName": "com.google.gson.MixedStreamTest",
      "timeInMs": 3793
    },
    {
      "fullQualifiedName": "com.google.gson.functional.ThrowableFunctionalTest",
      "timeInMs": 3793
    },
    {
      "fullQualifiedName": "com.google.gson.functional.EscapingTest",
      "timeInMs": 3739
    },
    {
      "fullQualifiedName": "com.google.gson.functional.ObjectTest",
      "timeInMs": 3748
    },
    {
      "fullQualifiedName": "com.google.gson.functional.CustomTypeAdaptersTest",
      "timeInMs": 3741
    },
    {
      "fullQualifiedName": "com.google.gson.CommentsTest",
      "timeInMs": 3894
    },
    {
      "fullQualifiedName": "com.google.gson.functional.CollectionTest",
      "timeInMs": 3720
    },
    {
      "fullQualifiedName": "com.google.gson.functional.PrimitiveTest",
      "timeInMs": 3736
    },
    {
      "fullQualifiedName": "com.google.gson.functional.RawSerializationTest",
      "timeInMs": 3783
    },
    {
      "fullQualifiedName": "com.google.gson.functional.EnumTest",
      "timeInMs": 3742
    },
    {
      "fullQualifiedName": "com.google.gson.functional.TypeVariableTest",
      "timeInMs": 3797
    },
    {
      "fullQualifiedName": "com.google.gson.functional.PrettyPrintingTest",
      "timeInMs": 3841
    },
    {
      "fullQualifiedName": "com.google.gson.functional.CircularReferenceTest",
      "timeInMs": 3801
    },
    {
      "fullQualifiedName": "com.google.gson.functional.UncategorizedTest",
      "timeInMs": 3900
    },
    {
      "fullQualifiedName": "com.google.gson.functional.MapAsArrayTypeAdapterTest",
      "timeInMs": 3788
    },
    {
      "fullQualifiedName": "com.google.gson.functional.ArrayTest",
      "timeInMs": 3873
    },
    {
      "fullQualifiedName": "com.google.gson.functional.NullObjectAndFieldTest",
      "timeInMs": 3856
    },
    {
      "fullQualifiedName": "com.google.gson.functional.InheritanceTest",
      "timeInMs": 3817
    },
    {
      "fullQualifiedName": "com.google.gson.functional.ParameterizedTypesTest",
      "timeInMs": 3837
    },
    {
      "fullQualifiedName": "com.google.gson.ObjectTypeAdapterTest",
      "timeInMs": 3696
    },
    {
      "fullQualifiedName": "com.google.gson.functional.StreamingTypeAdaptersTest",
      "timeInMs": 3848
    },
    {
      "fullQualifiedName": "com.google.gson.functional.JsonParserTest",
      "timeInMs": 3847
    },
    {
      "fullQualifiedName": "com.google.gson.functional.TreeTypeAdaptersTest",
      "timeInMs": 3775
    },
    {
      "fullQualifiedName": "com.google.gson.functional.ReadersWritersTest",
      "timeInMs": 3779
    },
    {
      "fullQualifiedName": "com.google.gson.DefaultMapJsonSerializerTest",
      "timeInMs": 3907
    },
    {
      "fullQualifiedName": "com.google.gson.functional.LeniencyTest",
      "timeInMs": 3814
    },
    {
      "fullQualifiedName": "com.google.gson.functional.InstanceCreatorTest",
      "timeInMs": 3772
    },
    {
      "fullQualifiedName": "com.google.gson.functional.DelegateTypeAdapterTest",
      "timeInMs": 3818
    },
    {
      "fullQualifiedName": "com.google.gson.functional.MoreSpecificTypeSerializationTest",
      "timeInMs": 3871
    },
    {
      "fullQualifiedName": "com.google.gson.JavaSerializationTest",
      "timeInMs": 3805
    },
    {
      "fullQualifiedName": "com.google.gson.functional.PrintFormattingTest",
      "timeInMs": 3786
    }
  ],
  "projectName": "gson"
}