{
  "classTimes": [
    {
      "fullQualifiedName": "com.urbanairship.api.client.UrbanAirshipClientTest",
      "timeInMs": 53132
    },
    {
      "fullQualifiedName": "com.urbanairship.api.schedule.ScheduleRequestTest",
      "timeInMs": 8656
    },
    {
      "fullQualifiedName": "com.urbanairship.api.schedule.ScheduleListingRequestTest",
      "timeInMs": 9026
    },
    {
      "fullQualifiedName": "com.urbanairship.api.client.ResponseTest",
      "timeInMs": 4352
    },
    {
      "fullQualifiedName": "com.urbanairship.api.schedule.SchedulePayloadDeserializerTest",
      "timeInMs": 52403
    },
    {
      "fullQualifiedName": "com.urbanairship.api.schedule.ScheduleValidatorTest",
      "timeInMs": 5224
    },
    {
      "fullQualifiedName": "com.urbanairship.api.experiments.parse.VariantDeserializerTest",
      "timeInMs": 10470
    },
    {
      "fullQualifiedName": "com.urbanairship.api.schedule.ScheduleResponseTest",
      "timeInMs": 7899
    },
    {
      "fullQualifiedName": "com.urbanairship.api.experiments.parse.VariantSerializerTest",
      "timeInMs": 9496
    },
    {
      "fullQualifiedName": "com.urbanairship.api.schedule.ListSchedulesResponseTest",
      "timeInMs": 78153
    },
    {
      "fullQualifiedName": "com.urbanairship.api.schedule.SchedulePayloadSerializerTest",
      "timeInMs": 87282
    }
  ],
  "projectName": "java-library_parent"
}