{
  "classTimes": [
    {
      "fullQualifiedName": "org.jsoup.integration.ParseTest",
      "timeInMs": 81935
    },
    {
      "fullQualifiedName": "org.jsoup.nodes.AttributeTest",
      "timeInMs": 14560
    },
    {
      "fullQualifiedName": "org.jsoup.safety.CleanerTest",
      "timeInMs": 151046
    },
    {
      "fullQualifiedName": "org.jsoup.nodes.AttributesTest",
      "timeInMs": 36696
    },
    {
      "fullQualifiedName": "org.jsoup.nodes.ElementTest",
      "timeInMs": 1063353
    },
    {
      "fullQualifiedName": "org.jsoup.nodes.NodeTest",
      "timeInMs": 42810
    },
    {
      "fullQualifiedName": "org.jsoup.parser.AttributeParseTest",
      "timeInMs": 15612
    },
    {
      "fullQualifiedName": "org.jsoup.select.ElementsTest",
      "timeInMs": 57151
    },
    {
      "fullQualifiedName": "org.jsoup.nodes.EntitiesTest",
      "timeInMs": 16500
    },
    {
      "fullQualifiedName": "org.jsoup.select.SelectorTest",
      "timeInMs": 144011
    },
    {
      "fullQualifiedName": "org.jsoup.parser.TokeniserTest",
      "timeInMs": 4305077
    },
    {
      "fullQualifiedName": "org.jsoup.nodes.FormElementTest",
      "timeInMs": 37692
    },
    {
      "fullQualifiedName": "org.jsoup.nodes.TextNodeTest",
      "timeInMs": 22229
    },
    {
      "fullQualifiedName": "org.jsoup.parser.TokeniserStateTest",
      "timeInMs": 25686
    },
    {
      "fullQualifiedName": "org.jsoup.helper.StringUtilTest",
      "timeInMs": 10201
    },
    {
      "fullQualifiedName": "org.jsoup.parser.HtmlParserTest",
      "timeInMs": 197477
    },
    {
      "fullQualifiedName": "org.jsoup.parser.XmlTreeBuilderTest",
      "timeInMs": 48300
    },
    {
      "fullQualifiedName": "org.jsoup.helper.W3CDomTest",
      "timeInMs": 107974
    },
    {
      "fullQualifiedName": "org.jsoup.nodes.DocumentTest",
      "timeInMs": 165092
    },
    {
      "fullQualifiedName": "org.jsoup.integration.ConnectTest",
      "timeInMs": 182517
    },
    {
      "fullQualifiedName": "org.jsoup.helper.DataUtilTest",
      "timeInMs": 46284
    }
  ],
  "projectName": "jsoup_parent"
}