{
  "classTimes": [
    {
      "fullQualifiedName": "org.apache.commons.lang3.time.FastDateParserTest",
      "timeInMs": 12568094
    },
    {
      "fullQualifiedName": "org.apache.commons.lang3.time.FastDatePrinterTimeZonesTest",
      "timeInMs": 3071757
    },
    {
      "fullQualifiedName": "org.apache.commons.lang3.time.DateUtilsTest",
      "timeInMs": 102172
    },
    {
      "fullQualifiedName": "org.apache.commons.lang3.time.FastDateParser_MoreOrLessTest",
      "timeInMs": 139991
    },
    {
      "fullQualifiedName": "org.apache.commons.lang3.time.FastDateParser_TimeZoneStrategyTest",
      "timeInMs": 372494
    }
  ],
  "projectName": "commons-lang_parent"
}