{
  "classTimes": [
    {
      "fullQualifiedName": "com.google.gson.functional.DefaultTypeAdaptersTest",
      "timeInMs": 91911
    },
    {
      "fullQualifiedName": "com.google.gson.functional.CollectionTest",
      "timeInMs": 52216
    },
    {
      "fullQualifiedName": "com.google.gson.functional.FieldExclusionTest",
      "timeInMs": 10908
    },
    {
      "fullQualifiedName": "com.google.gson.functional.CustomDeserializerTest",
      "timeInMs": 14949
    },
    {
      "fullQualifiedName": "com.google.gson.functional.SecurityTest",
      "timeInMs": 10655
    },
    {
      "fullQualifiedName": "com.google.gson.functional.EscapingTest",
      "timeInMs": 13322
    },
    {
      "fullQualifiedName": "com.google.gson.functional.MapTest",
      "timeInMs": 94401
    },
    {
      "fullQualifiedName": "com.google.gson.functional.ObjectTest",
      "timeInMs": 109729
    },
    {
      "fullQualifiedName": "com.google.gson.functional.JavaUtilConcurrentAtomicTest",
      "timeInMs": 8177
    },
    {
      "fullQualifiedName": "com.google.gson.functional.PrimitiveTest",
      "timeInMs": 21674
    },
    {
      "fullQualifiedName": "com.google.gson.functional.CustomTypeAdaptersTest",
      "timeInMs": 87051
    },
    {
      "fullQualifiedName": "com.google.gson.functional.ParameterizedTypesTest",
      "timeInMs": 106675
    },
    {
      "fullQualifiedName": "com.google.gson.functional.ExclusionStrategyFunctionalTest",
      "timeInMs": 33961
    },
    {
      "fullQualifiedName": "com.google.gson.functional.ReadersWritersTest",
      "timeInMs": 22932
    },
    {
      "fullQualifiedName": "com.google.gson.functional.CircularReferenceTest",
      "timeInMs": 13813
    },
    {
      "fullQualifiedName": "com.google.gson.functional.UncategorizedTest",
      "timeInMs": 12896
    },
    {
      "fullQualifiedName": "com.google.gson.DefaultMapJsonSerializerTest",
      "timeInMs": 13834
    },
    {
      "fullQualifiedName": "com.google.gson.functional.EnumTest",
      "timeInMs": 31554
    },
    {
      "fullQualifiedName": "com.google.gson.functional.JsonAdapterAnnotationOnClassesTest",
      "timeInMs": 35094
    },
    {
      "fullQualifiedName": "com.google.gson.functional.FieldNamingTest",
      "timeInMs": 11602
    },
    {
      "fullQualifiedName": "com.google.gson.MixedStreamTest",
      "timeInMs": 33142
    },
    {
      "fullQualifiedName": "com.google.gson.functional.JsonAdapterAnnotationOnFieldsTest",
      "timeInMs": 25781
    },
    {
      "fullQualifiedName": "com.google.gson.functional.NullObjectAndFieldTest",
      "timeInMs": 33711
    },
    {
      "fullQualifiedName": "com.google.gson.functional.NamingPolicyTest",
      "timeInMs": 24807
    },
    {
      "fullQualifiedName": "com.google.gson.GsonBuilderTest",
      "timeInMs": 7174
    },
    {
      "fullQualifiedName": "com.google.gson.functional.ArrayTest",
      "timeInMs": 9506
    },
    {
      "fullQualifiedName": "com.google.gson.functional.InstanceCreatorTest",
      "timeInMs": 13686
    },
    {
      "fullQualifiedName": "com.google.gson.functional.CustomSerializerTest",
      "timeInMs": 13373
    },
    {
      "fullQualifiedName": "com.google.gson.functional.MapAsArrayTypeAdapterTest",
      "timeInMs": 37212
    },
    {
      "fullQualifiedName": "com.google.gson.OverrideCoreTypeAdaptersTest",
      "timeInMs": 9896
    },
    {
      "fullQualifiedName": "com.google.gson.functional.VersioningTest",
      "timeInMs": 34235
    },
    {
      "fullQualifiedName": "com.google.gson.GsonTypeAdapterTest",
      "timeInMs": 6334
    },
    {
      "fullQualifiedName": "com.google.gson.functional.StreamingTypeAdaptersTest",
      "timeInMs": 48001
    },
    {
      "fullQualifiedName": "com.google.gson.functional.TypeAdapterPrecedenceTest",
      "timeInMs": 66003
    },
    {
      "fullQualifiedName": "com.google.gson.CommentsTest",
      "timeInMs": 7078
    },
    {
      "fullQualifiedName": "com.google.gson.functional.TypeVariableTest",
      "timeInMs": 22988
    },
    {
      "fullQualifiedName": "com.google.gson.functional.TypeHierarchyAdapterTest",
      "timeInMs": 254207
    },
    {
      "fullQualifiedName": "com.google.gson.LongSerializationPolicyTest",
      "timeInMs": 7250
    },
    {
      "fullQualifiedName": "com.google.gson.functional.DelegateTypeAdapterTest",
      "timeInMs": 9332
    },
    {
      "fullQualifiedName": "com.google.gson.JsonParserTest",
      "timeInMs": 51361
    },
    {
      "fullQualifiedName": "com.google.gson.JsonObjectTest",
      "timeInMs": 10280
    },
    {
      "fullQualifiedName": "com.google.gson.functional.RuntimeTypeAdapterFactoryFunctionalTest",
      "timeInMs": 8966
    },
    {
      "fullQualifiedName": "com.google.gson.regression.JsonAdapterNullSafeTest",
      "timeInMs": 6213
    },
    {
      "fullQualifiedName": "com.google.gson.functional.PrintFormattingTest",
      "timeInMs": 8820
    },
    {
      "fullQualifiedName": "com.google.gson.GsonTest",
      "timeInMs": 5801
    },
    {
      "fullQualifiedName": "com.google.gson.functional.ExposeFieldsTest",
      "timeInMs": 30307
    },
    {
      "fullQualifiedName": "com.google.gson.functional.JsonParserTest",
      "timeInMs": 14558
    },
    {
      "fullQualifiedName": "com.google.gson.functional.SerializedNameTest",
      "timeInMs": 7590
    },
    {
      "fullQualifiedName": "com.google.gson.functional.ConcurrencyTest",
      "timeInMs": 44848
    },
    {
      "fullQualifiedName": "com.google.gson.functional.InheritanceTest",
      "timeInMs": 67518
    },
    {
      "fullQualifiedName": "com.google.gson.functional.ThrowableFunctionalTest",
      "timeInMs": 14086
    },
    {
      "fullQualifiedName": "com.google.gson.functional.JsonTreeTest",
      "timeInMs": 27043
    },
    {
      "fullQualifiedName": "com.google.gson.ObjectTypeAdapterTest",
      "timeInMs": 5843
    },
    {
      "fullQualifiedName": "com.google.gson.functional.PrettyPrintingTest",
      "timeInMs": 8625
    },
    {
      "fullQualifiedName": "com.google.gson.functional.JavaUtilTest",
      "timeInMs": 7567
    },
    {
      "fullQualifiedName": "com.google.gson.functional.RawSerializationTest",
      "timeInMs": 17960
    },
    {
      "fullQualifiedName": "com.google.gson.functional.MoreSpecificTypeSerializationTest",
      "timeInMs": 74991
    },
    {
      "fullQualifiedName": "com.google.gson.functional.InterfaceTest",
      "timeInMs": 7264
    },
    {
      "fullQualifiedName": "com.google.gson.functional.TreeTypeAdaptersTest",
      "timeInMs": 11722
    }
  ],
  "projectName": "gson"
}