{
  "name": "com.github.mustachejava.PreTranslateTest",
  "nbOriginalTestCases": 1,
  "nbTestAmplified": 0,
  "testCases": [
    {
      "name": "testPretranslate_literalMutationString18_failAssert0",
      "nbInputAmplification": 1,
      "nbAssertionAmplification": 1
    },
    {
      "name": "testPretranslate_literalMutationString13_failAssert0",
      "nbInputAmplification": 1,
      "nbAssertionAmplification": 1
    },
    {
      "name": "testPretranslate_literalMutationString17_failAssert0",
      "nbInputAmplification": 1,
      "nbAssertionAmplification": 1
    }
  ]
}