{
  "classTimes": [
    {
      "fullQualifiedName": "com.github.mustachejava.TestWrapperCaching",
      "timeInMs": 24620
    },
    {
      "fullQualifiedName": "com.github.mustachejava.ExplicitMapNullTest",
      "timeInMs": 7380
    },
    {
      "fullQualifiedName": "com.github.mustachejava.AbstractClassTest",
      "timeInMs": 12079
    },
    {
      "fullQualifiedName": "com.github.mustachejava.AbsolutePartialReferenceTest",
      "timeInMs": 9620
    },
    {
      "fullQualifiedName": "com.github.mustachejava.inverter.InverterTest",
      "timeInMs": 10500
    }
  ],
  "projectName": "compiler"
}