{
  "classTimes": [
    {
      "fullQualifiedName": "com.google.gson.functional.MapTest",
      "timeInMs": 231024
    },
    {
      "fullQualifiedName": "com.google.gson.functional.NullObjectAndFieldTest",
      "timeInMs": 43258
    },
    {
      "fullQualifiedName": "com.google.gson.functional.CustomSerializerTest",
      "timeInMs": 17419
    },
    {
      "fullQualifiedName": "com.google.gson.functional.CustomTypeAdaptersTest",
      "timeInMs": 106539
    },
    {
      "fullQualifiedName": "com.google.gson.functional.ObjectTest",
      "timeInMs": 139971
    },
    {
      "fullQualifiedName": "com.google.gson.functional.MoreSpecificTypeSerializationTest",
      "timeInMs": 85430
    },
    {
      "fullQualifiedName": "com.google.gson.functional.PrimitiveTest",
      "timeInMs": 181457
    },
    {
      "fullQualifiedName": "com.google.gson.GsonTypeAdapterTest",
      "timeInMs": 14649
    },
    {
      "fullQualifiedName": "com.google.gson.functional.NamingPolicyTest",
      "timeInMs": 32609
    },
    {
      "fullQualifiedName": "com.google.gson.functional.ParameterizedTypesTest",
      "timeInMs": 127735
    },
    {
      "fullQualifiedName": "com.google.gson.functional.ConcurrencyTest",
      "timeInMs": 46329
    },
    {
      "fullQualifiedName": "com.google.gson.LongSerializationPolicyTest",
      "timeInMs": 9849
    },
    {
      "fullQualifiedName": "com.google.gson.functional.MapAsArrayTypeAdapterTest",
      "timeInMs": 43783
    },
    {
      "fullQualifiedName": "com.google.gson.reflect.TypeTokenTest",
      "timeInMs": 35247
    },
    {
      "fullQualifiedName": "com.google.gson.functional.FieldNamingTest",
      "timeInMs": 15624
    },
    {
      "fullQualifiedName": "com.google.gson.functional.PrimitiveCharacterTest",
      "timeInMs": 10459
    },
    {
      "fullQualifiedName": "com.google.gson.functional.PrettyPrintingTest",
      "timeInMs": 21566
    },
    {
      "fullQualifiedName": "com.google.gson.functional.InternationalizationTest",
      "timeInMs": 12614
    },
    {
      "fullQualifiedName": "com.google.gson.functional.EnumTest",
      "timeInMs": 40151
    },
    {
      "fullQualifiedName": "com.google.gson.functional.RawSerializationTest",
      "timeInMs": 22880
    },
    {
      "fullQualifiedName": "com.google.gson.functional.InheritanceTest",
      "timeInMs": 79406
    },
    {
      "fullQualifiedName": "com.google.gson.functional.TypeHierarchyAdapterTest",
      "timeInMs": 281180
    },
    {
      "fullQualifiedName": "com.google.gson.functional.JsonAdapterAnnotationOnFieldsTest",
      "timeInMs": 37862
    },
    {
      "fullQualifiedName": "com.google.gson.functional.StreamingTypeAdaptersTest",
      "timeInMs": 76229
    },
    {
      "fullQualifiedName": "com.google.gson.functional.JsonParserTest",
      "timeInMs": 25184
    },
    {
      "fullQualifiedName": "com.google.gson.functional.ExposeFieldsTest",
      "timeInMs": 37276
    },
    {
      "fullQualifiedName": "com.google.gson.functional.CustomDeserializerTest",
      "timeInMs": 19193
    },
    {
      "fullQualifiedName": "com.google.gson.functional.SerializedNameTest",
      "timeInMs": 10216
    },
    {
      "fullQualifiedName": "com.google.gson.functional.InstanceCreatorTest",
      "timeInMs": 18214
    },
    {
      "fullQualifiedName": "com.google.gson.JsonParserTest",
      "timeInMs": 58470
    },
    {
      "fullQualifiedName": "com.google.gson.GsonBuilderTest",
      "timeInMs": 10044
    },
    {
      "fullQualifiedName": "com.google.gson.MixedStreamTest",
      "timeInMs": 38198
    },
    {
      "fullQualifiedName": "com.google.gson.functional.VersioningTest",
      "timeInMs": 41897
    },
    {
      "fullQualifiedName": "com.google.gson.functional.StringTest",
      "timeInMs": 33304
    },
    {
      "fullQualifiedName": "com.google.gson.functional.ExclusionStrategyFunctionalTest",
      "timeInMs": 42575
    },
    {
      "fullQualifiedName": "com.google.gson.functional.EscapingTest",
      "timeInMs": 20817
    },
    {
      "fullQualifiedName": "com.google.gson.JsonObjectTest",
      "timeInMs": 10871
    },
    {
      "fullQualifiedName": "com.google.gson.functional.JsonAdapterAnnotationOnClassesTest",
      "timeInMs": 44929
    },
    {
      "fullQualifiedName": "com.google.gson.functional.ReadersWritersTest",
      "timeInMs": 31962
    },
    {
      "fullQualifiedName": "com.google.gson.functional.UncategorizedTest",
      "timeInMs": 19465
    },
    {
      "fullQualifiedName": "com.google.gson.functional.LeniencyTest",
      "timeInMs": 9301
    },
    {
      "fullQualifiedName": "com.google.gson.functional.ThrowableFunctionalTest",
      "timeInMs": 18411
    },
    {
      "fullQualifiedName": "com.google.gson.functional.PrintFormattingTest",
      "timeInMs": 8954
    },
    {
      "fullQualifiedName": "com.google.gson.functional.TypeAdapterPrecedenceTest",
      "timeInMs": 76134
    },
    {
      "fullQualifiedName": "com.google.gson.functional.ArrayTest",
      "timeInMs": 53498
    },
    {
      "fullQualifiedName": "com.google.gson.functional.JavaUtilConcurrentAtomicTest",
      "timeInMs": 19689
    },
    {
      "fullQualifiedName": "com.google.gson.functional.CircularReferenceTest",
      "timeInMs": 18925
    },
    {
      "fullQualifiedName": "com.google.gson.functional.JsonTreeTest",
      "timeInMs": 32524
    },
    {
      "fullQualifiedName": "com.google.gson.JavaSerializationTest",
      "timeInMs": 13529
    },
    {
      "fullQualifiedName": "com.google.gson.functional.TreeTypeAdaptersTest",
      "timeInMs": 14582
    },
    {
      "fullQualifiedName": "com.google.gson.functional.InterfaceTest",
      "timeInMs": 9666
    },
    {
      "fullQualifiedName": "com.google.gson.regression.JsonAdapterNullSafeTest",
      "timeInMs": 8736
    },
    {
      "fullQualifiedName": "com.google.gson.DefaultInetAddressTypeAdapterTest",
      "timeInMs": 11376
    },
    {
      "fullQualifiedName": "com.google.gson.ObjectTypeAdapterTest",
      "timeInMs": 12352
    },
    {
      "fullQualifiedName": "com.google.gson.functional.SecurityTest",
      "timeInMs": 14949
    },
    {
      "fullQualifiedName": "com.google.gson.functional.JavaUtilTest",
      "timeInMs": 11863
    },
    {
      "fullQualifiedName": "com.google.gson.DefaultMapJsonSerializerTest",
      "timeInMs": 23217
    },
    {
      "fullQualifiedName": "com.google.gson.GenericArrayTypeTest",
      "timeInMs": 11739
    },
    {
      "fullQualifiedName": "com.google.gson.functional.FieldExclusionTest",
      "timeInMs": 13489
    },
    {
      "fullQualifiedName": "com.google.gson.functional.JsonAdapterSerializerDeserializerTest",
      "timeInMs": 15801
    },
    {
      "fullQualifiedName": "com.google.gson.internal.GsonTypesTest",
      "timeInMs": 9383
    },
    {
      "fullQualifiedName": "com.google.gson.functional.TypeVariableTest",
      "timeInMs": 27456
    },
    {
      "fullQualifiedName": "com.google.gson.functional.RuntimeTypeAdapterFactoryFunctionalTest",
      "timeInMs": 11605
    },
    {
      "fullQualifiedName": "com.google.gson.ParameterizedTypeTest",
      "timeInMs": 11225
    },
    {
      "fullQualifiedName": "com.google.gson.functional.DelegateTypeAdapterTest",
      "timeInMs": 12464
    },
    {
      "fullQualifiedName": "com.google.gson.OverrideCoreTypeAdaptersTest",
      "timeInMs": 13196
    },
    {
      "fullQualifiedName": "com.google.gson.FieldAttributesTest",
      "timeInMs": 7549
    },
    {
      "fullQualifiedName": "com.google.gson.CommentsTest",
      "timeInMs": 9726
    }
  ],
  "projectName": "gson"
}