{
  "classTimes": [
    {
      "fullQualifiedName": "com.github.mustachejava.ExtensionTest",
      "timeInMs": 28656
    },
    {
      "fullQualifiedName": "com.github.mustachejava.ArraysIndexesTest",
      "timeInMs": 27003
    },
    {
      "fullQualifiedName": "com.github.mustachejava.MultipleRecursivePartialsTest",
      "timeInMs": 7499
    },
    {
      "fullQualifiedName": "com.github.mustachejava.functions.CommentTest",
      "timeInMs": 10871
    }
  ],
  "projectName": "compiler"
}