{
  "classTimes": [
    {
      "fullQualifiedName": "com.github.mustachejava.DotNotationTest",
      "timeInMs": 6037
    },
    {
      "fullQualifiedName": "com.github.mustachejava.PolymorphicClassTest",
      "timeInMs": 9712
    },
    {
      "fullQualifiedName": "com.github.mustachejava.FailOnMissingTest",
      "timeInMs": 8829
    },
    {
      "fullQualifiedName": "com.github.mustachejava.functions.TranslateBundleTest",
      "timeInMs": 7958
    },
    {
      "fullQualifiedName": "com.github.mustachejava.DelimiterTest",
      "timeInMs": 13865
    }
  ],
  "projectName": "compiler"
}