{
  "classTimes": [
    {
      "fullQualifiedName": "org.jsoup.helper.W3CDomTest",
      "timeInMs": 5434945
    },
    {
      "fullQualifiedName": "org.jsoup.parser.XmlTreeBuilderTest",
      "timeInMs": 33789
    },
    {
      "fullQualifiedName": "org.jsoup.helper.DataUtilTest",
      "timeInMs": 171507
    },
    {
      "fullQualifiedName": "org.jsoup.integration.ParseTest",
      "timeInMs": 320304
    },
    {
      "fullQualifiedName": "org.jsoup.select.SelectorTest",
      "timeInMs": 632012
    },
    {
      "fullQualifiedName": "org.jsoup.nodes.NodeTest",
      "timeInMs": 702908
    },
    {
      "fullQualifiedName": "org.jsoup.nodes.ElementTest",
      "timeInMs": 2426064
    },
    {
      "fullQualifiedName": "org.jsoup.safety.CleanerTest",
      "timeInMs": 1882758
    },
    {
      "fullQualifiedName": "org.jsoup.nodes.EntitiesTest",
      "timeInMs": 39794
    },
    {
      "fullQualifiedName": "org.jsoup.parser.AttributeParseTest",
      "timeInMs": 33990
    },
    {
      "fullQualifiedName": "org.jsoup.select.ElementsTest",
      "timeInMs": 452354
    },
    {
      "fullQualifiedName": "org.jsoup.parser.TokeniserTest",
      "timeInMs": 8040899
    },
    {
      "fullQualifiedName": "org.jsoup.nodes.FormElementTest",
      "timeInMs": 271252
    },
    {
      "fullQualifiedName": "org.jsoup.nodes.TextNodeTest",
      "timeInMs": 119867
    },
    {
      "fullQualifiedName": "org.jsoup.parser.TokeniserStateTest",
      "timeInMs": 42094
    },
    {
      "fullQualifiedName": "org.jsoup.helper.StringUtilTest",
      "timeInMs": 14094
    },
    {
      "fullQualifiedName": "org.jsoup.select.TraversorTest",
      "timeInMs": 50613
    },
    {
      "fullQualifiedName": "org.jsoup.parser.HtmlParserTest",
      "timeInMs": 1538775
    },
    {
      "fullQualifiedName": "org.jsoup.nodes.DocumentTest",
      "timeInMs": 254401
    },
    {
      "fullQualifiedName": "org.jsoup.integration.ConnectTest",
      "timeInMs": 790656
    }
  ],
  "projectName": "jsoup_parent"
}