{
  "name": "org.jsoup.integration.ConnectTest",
  "nbOriginalTestCases": 24,
  "nbTestAmplified": 0,
  "testCases": [
    {
      "name": "postFiles_literalMutationString1055_failAssert0",
      "nbInputAmplification": 1,
      "nbAssertionAmplification": 1
    },
    {
      "name": "postFiles_literalMutationString1060_failAssert0",
      "nbInputAmplification": 1,
      "nbAssertionAmplification": 1
    },
    {
      "name": "supportsDeflate_add3281",
      "nbInputAmplification": 2,
      "nbAssertionAmplification": 26
    }
  ]
}